AsyncFIFO/fifo_memory.v
module fifo_memory (
    input        wr_clk,
    input        wr_en,
    input  [2:0] wr_addr,
    input  [7:0] data_in,

    input        rd_clk,
    input        rd_en,
    input  [2:0] rd_addr,
    output reg [7:0] data_out
);

    // 8 locations, each 8 bits wide
    reg [7:0] mem [0:7];

    // Write operation
    always @(posedge wr_clk)
    begin
        if (wr_en)
            mem[wr_addr] <= data_in;
    end

    // Read operation
    always @(posedge rd_clk)
    begin
        if (rd_en)
            data_out <= mem[rd_addr];
    end

endmodule

AsyncFIFO/sync_r2w.v
module sync_r2w (
    input        wr_clk,
    input        wr_reset,
    input  [3:0] rd_gray,

    output reg [3:0] rd_gray_sync
);

    reg [3:0] sync_ff1;

    always @(posedge wr_clk or posedge wr_reset)
    begin
        if (wr_reset)
        begin
            sync_ff1     <= 4'b0000;
            rd_gray_sync <= 4'b0000;
        end
        else
        begin
            sync_ff1     <= rd_gray;
            rd_gray_sync <= sync_ff1;
        end
    end

endmodule

AsyncFIFO/sync_w2r.v
module sync_w2r (
    input        rd_clk,
    input        rd_reset,
    input  [3:0] wr_gray,

    output reg [3:0] wr_gray_sync
);

    reg [3:0] sync_ff1;

    always @(posedge rd_clk or posedge rd_reset)
    begin
        if (rd_reset)
        begin
            sync_ff1     <= 4'b0000;
            wr_gray_sync <= 4'b0000;
        end
        else
        begin
            sync_ff1     <= wr_gray;
            wr_gray_sync <= sync_ff1;
        end
    end

endmodule

AsyncFIFO/read_controller.v
module read_controller (
    input        rd_clk,
    input        rd_reset,
    input        rd_en,

    // Write pointer synchronized into read clock domain
    input  [3:0] wr_gray_sync,

    // Read pointer outputs
    output reg [3:0] rd_bin,
    output reg [3:0] rd_gray,

    // Memory address
    output [2:0] rd_addr,

    // FIFO status
    output reg empty
);

    // Next-state signals
    wire [3:0] rd_bin_next;
    wire [3:0] rd_gray_next;
    wire        empty_next;

    // Read pointer moves only when:
    // rd_en = 1 AND FIFO is not empty
    assign rd_bin_next = rd_bin + (rd_en && !empty);

    // Binary to Gray conversion
    assign rd_gray_next = rd_bin_next ^ (rd_bin_next >> 1);

    // Lower 3 bits select one of the 8 memory locations
    assign rd_addr = rd_bin[2:0];

    // FIFO EMPTY detection
    assign empty_next = (rd_gray_next == wr_gray_sync);

    // Register read pointer and EMPTY flag
    always @(posedge rd_clk or posedge rd_reset)
    begin
        if (rd_reset)
        begin
            rd_bin  <= 4'b0000;
            rd_gray <= 4'b0000;
            empty   <= 1'b1;
        end
        else
        begin
            rd_bin  <= rd_bin_next;
            rd_gray <= rd_gray_next;
            empty   <= empty_next;
        end
    end

endmodule

AsyncFIFO/write_controller.v
module write_controller (
    input        wr_clk,
    input        wr_reset,
    input        wr_en,

    // Read pointer synchronized into write clock domain
    input  [3:0] rd_gray_sync,

    // Write pointer outputs
    output reg [3:0] wr_bin,
    output reg [3:0] wr_gray,

    // Memory address
    output [2:0] wr_addr,

    // FIFO status
    output reg full
);

    // Next-state signals
    wire [3:0] wr_bin_next;
    wire [3:0] wr_gray_next;
    wire        full_next;

    // Write pointer moves only when:
    // wr_en = 1 AND FIFO is not full
    assign wr_bin_next = wr_bin + (wr_en && !full);

    // Binary to Gray conversion
    assign wr_gray_next = wr_bin_next ^ (wr_bin_next >> 1);

    // Lower 3 bits select one of the 8 memory locations
    assign wr_addr = wr_bin[2:0];

    // FIFO FULL detection
    // For an 8-depth FIFO, invert the upper two bits
    // of the synchronized read Gray pointer.
    assign full_next =
        (wr_gray_next ==
         {~rd_gray_sync[3:2], rd_gray_sync[1:0]});

    // Register write pointer and FULL flag
    always @(posedge wr_clk or posedge wr_reset)
    begin
        if (wr_reset)
        begin
            wr_bin  <= 4'b0000;
            wr_gray <= 4'b0000;
            full    <= 1'b0;
        end
        else
        begin
            wr_bin  <= wr_bin_next;
            wr_gray <= wr_gray_next;
            full    <= full_next;
        end
    end

endmodule

AsyncFIFO/async_fifo_top.v
module async_fifo_top (
    input        wr_clk,
    input        rd_clk,

    input        wr_reset,
    input        rd_reset,

    input        wr_en,
    input        rd_en,

    input  [7:0] data_in,
    output [7:0] data_out,

    output       full,
    output       empty
);

    // Write-side signals
    wire [3:0] wr_bin;
    wire [3:0] wr_gray;
    wire [2:0] wr_addr;

    // Read-side signals
    wire [3:0] rd_bin;
    wire [3:0] rd_gray;
    wire [2:0] rd_addr;

    // Synchronized pointer signals
    wire [3:0] wr_gray_sync;
    wire [3:0] rd_gray_sync;


    //==================================================
    // WRITE CONTROLLER
    //==================================================
    write_controller WC (
        .wr_clk       (wr_clk),
        .wr_reset     (wr_reset),
        .wr_en        (wr_en),
        .rd_gray_sync (rd_gray_sync),

        .wr_bin       (wr_bin),
        .wr_gray      (wr_gray),
        .wr_addr      (wr_addr),
        .full         (full)
    );


    //==================================================
    // READ CONTROLLER
    //==================================================
    read_controller RC (
        .rd_clk       (rd_clk),
        .rd_reset     (rd_reset),
        .rd_en        (rd_en),
        .wr_gray_sync (wr_gray_sync),

        .rd_bin       (rd_bin),
        .rd_gray      (rd_gray),
        .rd_addr      (rd_addr),
        .empty        (empty)
    );


    //==================================================
    // WRITE-TO-READ SYNCHRONIZER
    //==================================================
    sync_w2r SW2R (
        .rd_clk       (rd_clk),
        .rd_reset     (rd_reset),
        .wr_gray      (wr_gray),

        .wr_gray_sync (wr_gray_sync)
    );


    //==================================================
    // READ-TO-WRITE SYNCHRONIZER
    //==================================================
    sync_r2w SR2W (
        .wr_clk       (wr_clk),
        .wr_reset     (wr_reset),
        .rd_gray      (rd_gray),

        .rd_gray_sync (rd_gray_sync)
    );


    //==================================================
    // FIFO MEMORY
    //==================================================
    fifo_memory MEM (
        .wr_clk   (wr_clk),
        .wr_en    (wr_en && !full),
        .wr_addr  (wr_addr),
        .data_in  (data_in),

        .rd_clk   (rd_clk),
        .rd_en    (rd_en && !empty),
        .rd_addr  (rd_addr),
        .data_out (data_out)
    );

endmodule

AsyncFIFO/async_fifo_tb.v
`timescale 1ns/1ps

module async_fifo_tb;

    // Clock and reset signals
    reg wr_clk;
    reg rd_clk;
    reg wr_reset;
    reg rd_reset;

    // FIFO control signals
    reg wr_en;
    reg rd_en;

    // Data signals
    reg  [7:0] data_in;
    wire [7:0] data_out;

    // FIFO status
    wire full;
    wire empty;


    //==================================================
    // DUT - Device Under Test
    //==================================================
    async_fifo_top DUT (
        .wr_clk   (wr_clk),
        .rd_clk   (rd_clk),

        .wr_reset (wr_reset),
        .rd_reset (rd_reset),

        .wr_en    (wr_en),
        .rd_en    (rd_en),

        .data_in  (data_in),
        .data_out (data_out),

        .full     (full),
        .empty    (empty)
    );


    //==================================================
    // WRITE CLOCK
    // Period = 10 ns
    //==================================================
    initial begin
        wr_clk = 1'b0;
        forever #5 wr_clk = ~wr_clk;
    end


    //==================================================
    // READ CLOCK
    // Period = 14 ns
    //==================================================
    initial begin
        rd_clk = 1'b0;
        forever #7 rd_clk = ~rd_clk;
    end


    //==================================================
    // WAVEFORM
    //==================================================
    initial begin
        $dumpfile("async_fifo.vcd");
        $dumpvars(0, async_fifo_tb);
    end


    //==================================================
    // TEST SEQUENCE
    //==================================================
    initial begin

        // Initial values
        wr_reset = 1'b1;
        rd_reset = 1'b1;

        wr_en = 1'b0;
        rd_en = 1'b0;

        data_in = 8'h00;


        // --------------------------------------------
        // RESET
        // --------------------------------------------
        #20;

        wr_reset = 1'b0;
        rd_reset = 1'b0;


        // --------------------------------------------
        // WRITE 8 DATA VALUES
        // --------------------------------------------

        @(negedge wr_clk);
        wr_en   = 1'b1;
        data_in = 8'h11;

        @(negedge wr_clk);
        data_in = 8'h22;

        @(negedge wr_clk);
        data_in = 8'h33;

        @(negedge wr_clk);
        data_in = 8'h44;

        @(negedge wr_clk);
        data_in = 8'h55;

        @(negedge wr_clk);
        data_in = 8'h66;

        @(negedge wr_clk);
        data_in = 8'h77;

        @(negedge wr_clk);
        data_in = 8'h88;

        @(negedge wr_clk);
        wr_en = 1'b0;


        // --------------------------------------------
        // WAIT FOR POINTER SYNCHRONIZATION
        // --------------------------------------------
        #50;


        // --------------------------------------------
        // READ 8 DATA VALUES
        // --------------------------------------------

        @(negedge rd_clk);
        rd_en = 1'b1;

        @(negedge rd_clk);
        @(negedge rd_clk);
        @(negedge rd_clk);
        @(negedge rd_clk);
        @(negedge rd_clk);
        @(negedge rd_clk);
        @(negedge rd_clk);

        @(negedge rd_clk);
        rd_en = 1'b0;


        // --------------------------------------------
        // WAIT
        // --------------------------------------------
        #30;

        $finish;

    end


    //==================================================
    // MONITOR
    //==================================================
    initial begin

        $monitor(
            "TIME=%0t | wr_clk=%b rd_clk=%b | wr_en=%b rd_en=%b | data_in=%h data_out=%h | FULL=%b EMPTY=%b",
            $time,
            wr_clk,
            rd_clk,
            wr_en,
            rd_en,
            data_in,
            data_out,
            full,
            empty
        );

    end

endmodule

AsyncFIFO/async_fifo.vcd
$date
	Tue Sep 15 19:37:45 2026
$end
$version
	Icarus Verilog
$end
$timescale
	1ps
$end
$scope module async_fifo_tb $end
$var wire 1 ! full $end
$var wire 1 " empty $end
$var wire 8 # data_out [7:0] $end
$var reg 8 $ data_in [7:0] $end
$var reg 1 % rd_clk $end
$var reg 1 & rd_en $end
$var reg 1 ' rd_reset $end
$var reg 1 ( wr_clk $end
$var reg 1 ) wr_en $end
$var reg 1 * wr_reset $end
$scope module DUT $end
$var wire 8 + data_in [7:0] $end
$var wire 1 % rd_clk $end
$var wire 1 & rd_en $end
$var wire 1 ' rd_reset $end
$var wire 1 ( wr_clk $end
$var wire 1 ) wr_en $end
$var wire 1 * wr_reset $end
$var wire 4 , wr_gray_sync [3:0] $end
$var wire 4 - wr_gray [3:0] $end
$var wire 4 . wr_bin [3:0] $end
$var wire 3 / wr_addr [2:0] $end
$var wire 4 0 rd_gray_sync [3:0] $end
$var wire 4 1 rd_gray [3:0] $end
$var wire 4 2 rd_bin [3:0] $end
$var wire 3 3 rd_addr [2:0] $end
$var wire 1 ! full $end
$var wire 1 " empty $end
$var wire 8 4 data_out [7:0] $end
$scope module MEM $end
$var wire 8 5 data_in [7:0] $end
$var wire 1 % rd_clk $end
$var wire 1 6 rd_en $end
$var wire 1 ( wr_clk $end
$var wire 1 7 wr_en $end
$var wire 3 8 wr_addr [2:0] $end
$var wire 3 9 rd_addr [2:0] $end
$var reg 8 : data_out [7:0] $end
$upscope $end
$scope module RC $end
$var wire 1 % rd_clk $end
$var wire 1 & rd_en $end
$var wire 4 ; rd_gray_next [3:0] $end
$var wire 1 ' rd_reset $end
$var wire 4 < wr_gray_sync [3:0] $end
$var wire 4 = rd_bin_next [3:0] $end
$var wire 3 > rd_addr [2:0] $end
$var wire 1 ? empty_next $end
$var reg 1 " empty $end
$var reg 4 @ rd_bin [3:0] $end
$var reg 4 A rd_gray [3:0] $end
$upscope $end
$scope module SR2W $end
$var wire 4 B rd_gray [3:0] $end
$var wire 1 ( wr_clk $end
$var wire 1 * wr_reset $end
$var reg 4 C rd_gray_sync [3:0] $end
$var reg 4 D sync_ff1 [3:0] $end
$upscope $end
$scope module SW2R $end
$var wire 1 % rd_clk $end
$var wire 1 ' rd_reset $end
$var wire 4 E wr_gray [3:0] $end
$var reg 4 F sync_ff1 [3:0] $end
$var reg 4 G wr_gray_sync [3:0] $end
$upscope $end
$scope module WC $end
$var wire 4 H rd_gray_sync [3:0] $end
$var wire 1 ( wr_clk $end
$var wire 1 ) wr_en $end
$var wire 4 I wr_gray_next [3:0] $end
$var wire 1 * wr_reset $end
$var wire 4 J wr_bin_next [3:0] $end
$var wire 3 K wr_addr [2:0] $end
$var wire 1 L full_next $end
$var reg 1 ! full $end
$var reg 4 M wr_bin [3:0] $end
$var reg 4 N wr_gray [3:0] $end
$upscope $end
$upscope $end
$upscope $end
$enddefinitions $end
$comment Show the parameter values. $end
$dumpall
$end
#0
$dumpvars
b0 N
b0 M
0L
b0 K
b0 J
b0 I
b0 H
b0 G
b0 F
b0 E
b0 D
b0 C
b0 B
b0 A
b0 @
1?
b0 >
b0 =
b0 <
b0 ;
bx :
b0 9
b0 8
07
06
b0 5
bx 4
b0 3
b0 2
b0 1
b0 0
b0 /
b0 .
b0 -
b0 ,
b0 +
1*
0)
0(
1'
0&
0%
b0 $
bx #
1"
0!
$end
#5000
1(
#7000
1%
#10000
0(
#14000
0%
#15000
1(
#20000
b1 I
17
b1 J
b10001 $
b10001 +
b10001 5
1)
0(
0'
0*
#21000
1%
#25000
b11 I
b1 /
b1 8
b1 K
b1 -
b1 E
b1 N
b10 J
b1 .
b1 M
1(
#28000
0%
#30000
b100010 $
b100010 +
b100010 5
0(
#35000
b10 I
b10 /
b10 8
b10 K
b11 -
b11 E
b11 N
b11 J
b10 .
b10 M
b1 F
1(
1%
#40000
b110011 $
b110011 +
b110011 5
0(
#42000
0%
#45000
b110 I
b11 /
b11 8
b11 K
b10 -
b10 E
b10 N
b100 J
b11 .
b11 M
1(
#49000
0?
b1 ,
b1 <
b1 G
b10 F
1%
#50000
b1000100 $
b1000100 +
b1000100 5
0(
#55000
b111 I
b100 /
b100 8
b100 K
b110 -
b110 E
b110 N
b101 J
b100 .
b100 M
1(
#56000
0%
#60000
b1010101 $
b1010101 +
b1010101 5
0(
#63000
b10 ,
b10 <
b10 G
b110 F
0"
1%
#65000
b101 I
b101 /
b101 8
b101 K
b111 -
b111 E
b111 N
b110 J
b101 .
b101 M
1(
#70000
b1100110 $
b1100110 +
b1100110 5
0(
0%
#75000
b100 I
b110 /
b110 8
b110 K
b101 -
b101 E
b101 N
b111 J
b110 .
b110 M
1(
#77000
b110 ,
b110 <
b110 G
b101 F
1%
#80000
b1110111 $
b1110111 +
b1110111 5
0(
#84000
0%
#85000
1L
b1100 I
b111 /
b111 8
b111 K
b100 -
b100 E
b100 N
b1000 J
b111 .
b111 M
1(
#90000
b10001000 $
b10001000 +
b10001000 5
0(
#91000
b101 ,
b101 <
b101 G
b100 F
1%
#95000
07
1L
b1100 I
b0 /
b0 8
b0 K
1!
b1100 -
b1100 E
b1100 N
b1000 J
b1000 .
b1000 M
1(
#98000
0%
#100000
0)
0(
#105000
b100 ,
b100 <
b100 G
b1100 F
1(
1%
#110000
0(
#112000
0%
#115000
1(
#119000
b1100 ,
b1100 <
b1100 G
1%
#120000
0(
#125000
1(
#126000
0%
#130000
0(
#133000
1%
#135000
1(
#140000
0(
0%
#145000
1(
#147000
1%
#150000
0(
#154000
b1 ;
16
b1 =
1&
0%
#155000
1(
#160000
0(
#161000
b11 ;
b1 3
b1 9
b1 >
b10001 #
b10001 4
b10001 :
b1 1
b1 A
b1 B
b10 =
b1 2
b1 @
1%
#165000
b1 D
1(
#168000
0%
#170000
0(
#175000
0L
b10 ;
b10 3
b10 9
b10 >
b1 0
b1 C
b1 H
b100010 #
b100010 4
b100010 :
b11 1
b11 A
b11 B
b11 =
b10 2
b10 @
1(
1%
#180000
0(
#182000
0%
#185000
b11 D
0!
1(
#189000
b110 ;
b11 3
b11 9
b11 >
b110011 #
b110011 4
b110011 :
b10 1
b10 A
b10 B
b100 =
b11 2
b11 @
1%
#190000
0(
#195000
b11 0
b11 C
b11 H
b10 D
1(
#196000
0%
#200000
0(
#203000
b111 ;
b100 3
b100 9
b100 >
b1000100 #
b1000100 4
b1000100 :
b110 1
b110 A
b110 B
b101 =
b100 2
b100 @
1%
#205000
b10 0
b10 C
b10 H
b110 D
1(
#210000
0(
0%
#215000
b110 0
b110 C
b110 H
1(
#217000
b101 ;
b101 3
b101 9
b101 >
b1010101 #
b1010101 4
b1010101 :
b111 1
b111 A
b111 B
b110 =
b101 2
b101 @
1%
#220000
0(
#224000
0%
#225000
b111 D
1(
#230000
0(
#231000
b100 ;
b110 3
b110 9
b110 >
b1100110 #
b1100110 4
b1100110 :
b101 1
b101 A
b101 B
b111 =
b110 2
b110 @
1%
#235000
b111 0
b111 C
b111 H
b101 D
1(
#238000
0%
#240000
0(
#245000
1?
b1100 ;
b111 3
b111 9
b111 >
b101 0
b101 C
b101 H
b1110111 #
b1110111 4
b1110111 :
b100 1
b100 A
b100 B
b1000 =
b111 2
b111 @
1(
1%
#250000
0(
#252000
0%
#255000
b100 D
1(
#259000
06
1?
b1100 ;
b0 3
b0 9
b0 >
b10001000 #
b10001000 4
b10001000 :
1"
b1100 1
b1100 A
b1100 B
b1000 =
b1000 2
b1000 @
1%
#260000
0(
#265000
b100 0
b100 C
b100 H
b1100 D
1(
#266000
0&
0%
#270000
0(
#273000
1%
#275000
b1100 0
b1100 C
b1100 H
1(
